aegisblade/__init__.py
aegisblade/__version__.py
aegisblade/application.py
aegisblade/capabilities.py
aegisblade/client.py
aegisblade/data_store.py
aegisblade/errors.py
aegisblade/job.py
aegisblade/job_config.py
aegisblade/ApiModels/__init__.py
aegisblade/ApiModels/payloads.py
aegisblade/ApiModels/responses.py
aegisblade/_internal/__init__.py
aegisblade/_internal/api_consumer.py
aegisblade/_internal/application_context_file.py
aegisblade/_internal/application_execution_context.py
aegisblade/_internal/application_execution_context_collector.py
aegisblade/_internal/application_package_info.py
aegisblade/_internal/atrace.py
aegisblade/_internal/cached_std_lib_modules.py
aegisblade/_internal/command.py
aegisblade/_internal/environment.py
aegisblade/_internal/json_wrapper.py
aegisblade/_internal/task_info.py
aegisblade/_internal/_cached_stdlib_modules/__init__.py
aegisblade/_internal/_cached_stdlib_modules/v2_6.py
aegisblade/_internal/_cached_stdlib_modules/v2_7.py
aegisblade/_internal/_cached_stdlib_modules/v3_6.py
aegisblade-0.2.0.dist-info/LICENSE
aegisblade-0.2.0.dist-info/METADATA
aegisblade-0.2.0.dist-info/WHEEL
aegisblade-0.2.0.dist-info/top_level.txt
aegisblade-0.2.0.dist-info/RECORD
