Metadata-Version: 2.1
Name: aegisblade
Version: 0.2.0
Summary: Deploy & run your code in a single function call.
Home-page: https://www.aegisblade.com/
Author: AegisBlade
Author-email: welovedevs@aegisblade.com
License: LGPL2.1
Project-URL: Docs, https://www.aegisblade.com/docs
Project-URL: Github, https://github.com/aegisblade/aegis-python
Project-URL: Bug Reports, https://github.com/aegisblade/aegis-python/issues
Project-URL: Reference, https://www.aegisblade.com/docs/reference/python
Keywords: aegisblade server aws ec2 devops infrastructure as code IaC serverless kubernetes
Platform: UNKNOWN
Classifier: Intended Audience :: Developers
Classifier: License :: OSI Approved :: GNU Lesser General Public License v2 or later (LGPLv2+)
Classifier: Operating System :: POSIX :: Linux
Classifier: Operating System :: MacOS :: MacOS X
Classifier: Operating System :: Microsoft :: Windows
Classifier: Programming Language :: Python
Classifier: Programming Language :: Python :: 2.7
Classifier: Programming Language :: Python :: 3
Classifier: Programming Language :: Python :: 3.3
Classifier: Programming Language :: Python :: 3.4
Classifier: Programming Language :: Python :: 3.5
Classifier: Programming Language :: Python :: 3.6
Classifier: Topic :: Internet
Classifier: Topic :: System :: Distributed Computing
Classifier: Topic :: Software Development :: Libraries :: Python Modules
Requires-Python: >=2.7
Requires-Dist: requests (==2.20.1)
Requires-Dist: typing (==3.6.4)
Requires-Dist: cloudpickle (==1.2.2)
